pyskyqhub/__init__.py
pyskyqhub/const.py
pyskyqhub/skyq_hub.py
pyskyqhub/version.py
pyskyqhub-0.1.9.dist-info/LICENSE
pyskyqhub-0.1.9.dist-info/METADATA
pyskyqhub-0.1.9.dist-info/WHEEL
pyskyqhub-0.1.9.dist-info/top_level.txt
pyskyqhub-0.1.9.dist-info/RECORD
