Metadata-Version: 2.1
Name: pyskyqhub
Version: 0.1.9
Summary: Library for Sky Q hub
Home-page: https://github.com/RogerSelwyn/skyq_hub
Author: Roger Selwyn
Author-email: roger.selwyn@nomail.com
License: MIT
Keywords: SKYQ hub
Platform: UNKNOWN
Requires-Python: >=3.7
Requires-Dist: aiohttp (>=3.6.2)
